[
  {
    "name": "4 Dormeurs Et 1 Marteau Piqueur",
    "lineup": [
      {
        "name": "Switzerland23",
        "email": "florent.chevre@gmail.com"
      },
      {
        "name": "J0k3r",
        "email": "Jeremys_421@hotmail.com"
      },
      {
        "name": "QH_Korea_Spirit",
        "email": "andeol@mair.ch"
      },
      {
        "name": "raghna",
        "email": "sebba1080@hotmail.com"
      },
      {
        "name": "Crysis",
        "email": "sechs7406@gmail.com"
      }
    ]
  },
  {
    "name": "Absolute Frost",
    "lineup": [
      {
        "name": "Etona",
        "email": "Kevin008_2@hotmail.com"
      },
      {
        "name": "ABFT Gab",
        "email": "gabriel@gregtex.com"
      },
      {
        "name": "LegenDarryl",
        "email": "darryl.luethi@gmail.com"
      },
      {
        "name": "LenZy",
        "email": "xLenZy@outlook.com"
      },
      {
        "name": "michelxdlol",
        "email": "michelxdlol@hotmail.com"
      }
    ]
  },
  {
    "name": "And Another One",
    "lineup": [
      {
        "name": "Hilaos",
        "email": "manuelvidal67@gmail.com"
      },
      {
        "name": "Reavens",
        "email": "steve.bagnoud@hotmail.com"
      },
      {
        "name": "Szay",
        "email": "alexandrefig.1996@hotmail.com"
      },
      {
        "name": "là gamin",
        "email": "mdx_crew_fab@hotmail.com"
      }
    ]
  },
  {
    "name": "Bronze Korean",
    "lineup": [
      {
        "name": "Sandroo",
        "email": "drofigueiredowartek@gmail.com"
      },
      {
        "name": "Nolax",
        "email": "xyoyo999@gmail.com"
      },
      {
        "name": "En0x",
        "email": "jeffmottaz@gmail.com"
      },
      {
        "name": "Arkangell",
        "email": "tioneb92@gmail.com"
      }
    ]
  },
  {
    "name": "Clooz",
    "lineup": [
      {
        "name": "kinkaz",
        "email": "tim@bornick.com"
      },
      {
        "name": "razzorlol",
        "email": "mereuta.cristian@gmail.com"
      },
      {
        "name": "almil36",
        "email": "alain@milliet.ch"
      },
      {
        "name": "Tapolet",
        "email": "jeremi.guerra@gmail.com"
      },
      {
        "name": "Nyamaru",
        "email": "steveke0204@gmail.com"
      }
    ]
  },
  {
    "name": "Coucouch Clan",
    "lineup": [
      {
        "name": "Nyloth",
        "email": "frederic.saam@gmail.com"
      },
      {
        "name": "Sigvent",
        "email": "michaelduong00@hotmail.com"
      },
      {
        "name": "Umberfury",
        "email": "kewinduong95@gmail.com"
      },
      {
        "name": "Lanzmaster",
        "email": "lanzmaster@hotmail.com"
      }
    ]
  },
  {
    "name": "Csg Brotherhood",
    "lineup": [
      {
        "name": "Zaragord",
        "email": "zaragord@gmail.com"
      },
      {
        "name": "SSJ",
        "email": "david.hnrqs@eduge.ch"
      },
      {
        "name": "Keikowah",
        "email": "Nuno10@hotmail.fr"
      },
      {
        "name": "Safir",
        "email": "Jony-safir@hotmail.com"
      },
      {
        "name": "Lombreur",
        "email": "Minitutu007@gmail.com"
      }
    ]
  },
  {
    "name": "E-lvet Darkwall",
    "lineup": [
      {
        "name": "wipix",
        "email": "wipixdreed@gmail.com"
      },
      {
        "name": "ELVmarksman",
        "email": "a.gomes115@hotmail.fr"
      },
      {
        "name": "Aloa",
        "email": "aloa.jack@hotmail.ch"
      },
      {
        "name": "Xargas",
        "email": "jonathan.rollier@hotmail.com"
      },
      {
        "name": "Swiiizzz",
        "email": "overbrained@gmail.com"
      }
    ]
  },
  {
    "name": "E-lvets Firststone",
    "lineup": [
      {
        "name": "koobsky",
        "email": "kueki5@hotmail.com"
      },
      {
        "name": "Swisside",
        "email": "boris0388@bluewin.ch"
      },
      {
        "name": "tormento",
        "email": "andres.gomesiglesias@gmail.com"
      },
      {
        "name": "Atrex25",
        "email": "valentin.jalley@gmail.com"
      }
    ]
  },
  {
    "name": "E-lvets Val Hey",
    "lineup": [
      {
        "name": "Elentir",
        "email": "Roxxass12@gmail.com"
      },
      {
        "name": "StealMaster",
        "email": "thomas.germanier@yahoo.fr"
      },
      {
        "name": "ratchik",
        "email": "olivier.jalley@hotmail.fr"
      },
      {
        "name": "Magimiauu",
        "email": "Loan.buffet@live.fr"
      },
      {
        "name": "Titdody",
        "email": "titdody@gmail.com"
      }
    ]
  },
  {
    "name": "Eca Jolly Chimps",
    "lineup": [
      {
        "name": "OracleArts",
        "email": "CloverGamingc@gmail.com"
      },
      {
        "name": "Monke",
        "email": "noe.rossel@bluewin.ch"
      },
      {
        "name": "Resh",
        "email": "Kevin-1203@hotmail.fr"
      },
      {
        "name": "qeo",
        "email": "vlp20victor@hotmail.com"
      },
      {
        "name": "Ono",
        "email": "linkos08@gmail.com"
      }
    ]
  },
  {
    "name": "Imperium",
    "lineup": [
      {
        "name": "OryZon Daiki",
        "email": "louis.the.best@hotmail.com"
      },
      {
        "name": "Ssoap",
        "email": "greg.stuhlmann@hotmail.de"
      },
      {
        "name": "OryZon Kirai",
        "email": "monnard.stephane@gmail.com"
      },
      {
        "name": "OryZon Sharkwaves",
        "email": "Thesharkwave96@gmail.com"
      },
      {
        "name": "imp Twicky",
        "email": "Olivier.porret@me.com"
      },
      {
        "name": "Sam Ecchi",
        "email": "sam_piasio@hotmail.com"
      }
    ]
  },
  {
    "name": "Lf Jungle Pls",
    "lineup": [
      {
        "name": "m4ttou",
        "email": "mgirard92@gmail.com"
      },
      {
        "name": "soupalacourge",
        "email": "kesi666@hotmail.com"
      },
      {
        "name": "shanou",
        "email": "lea.michellealves@gmail.com"
      },
      {
        "name": "Sweezhy",
        "email": "sweezhy@hotmail.fr"
      }
    ]
  },
  {
    "name": "Oxystyle",
    "lineup": [
      {
        "name": "JAROUSSE Florian",
        "email": "florian.jarousse@hotmail.fr"
      },
      {
        "name": "Wolv3rZ",
        "email": "nicolas.gadiollet01@gmail.com"
      },
      {
        "name": "gadio01",
        "email": "gadioponey@gmail.com"
      },
      {
        "name": "gadio001",
        "email": "nathangadiollet@msn.com"
      },
      {
        "name": "wort05",
        "email": "ricardo.dealmeidaesilva@gmail.com"
      }
    ]
  },
  {
    "name": "Patatogaming",
    "lineup": [
      {
        "name": "Kecks",
        "email": "bad22kid@hotmail.com"
      },
      {
        "name": "droidekas",
        "email": "nrichard1990@gmail.com"
      },
      {
        "name": "Steams",
        "email": "anthasit.michel@gmail.com"
      },
      {
        "name": "kldiep",
        "email": "kldiep@hotmail.com"
      },
      {
        "name": "EvolveD",
        "email": "isengrinn@gmail.com"
      }
    ]
  },
  {
    "name": "pØlø",
    "lineup": [
      {
        "name": "ShawnThePsycho",
        "email": "xwasamenx@gmail.com"
      },
      {
        "name": "Wasamen",
        "email": "quentin.salomon@heig-vd.ch"
      },
      {
        "name": "Pierre Walter",
        "email": "Pierre.Walter.2010@gmail.com"
      }
    ]
  },
  {
    "name": "Soupeur Hot Crew",
    "lineup": [
      {
        "name": "Green Pepper",
        "email": "swissgreenpepper@gmail.com"
      },
      {
        "name": "Sacavain",
        "email": "sacavain.merlot@gmail.com"
      },
      {
        "name": "Johnson235",
        "email": "basile.roulet@hotmail.fr"
      }
    ]
  },
  {
    "name": "Supercalifragilisticexpialidocious",
    "lineup": [
      {
        "name": "Captainduf",
        "email": "e_duf@hotmail.com"
      },
      {
        "name": "Mcbarrete",
        "email": "marcmaten@msn.com"
      },
      {
        "name": "Meelo",
        "email": "jerome.kaempf@gmail.com"
      },
      {
        "name": "swoke",
        "email": "own.kenpachi@gmail.com"
      },
      {
        "name": "Brownies",
        "email": "mrccrmcc96@gmail.com"
      }
    ]
  },
  {
    "name": "Tilt Runs Deep With Us",
    "lineup": [
      {
        "name": "Nyah0n",
        "email": "poulardremi20@gmail.com"
      },
      {
        "name": "Enoria",
        "email": "imoan255@hotmail.com"
      },
      {
        "name": "Vahlraven",
        "email": "virgil.inalbon@gmail.com"
      },
      {
        "name": "overloid",
        "email": "rock_lee22@hotmail.com"
      }
    ]
  },
  {
    "name": "Tu Crois Tu Me Connais",
    "lineup": [
      {
        "name": "bbaga",
        "email": "baeriivan@gmail.com"
      },
      {
        "name": "Shacoca",
        "email": "silvin10@gmail.com"
      },
      {
        "name": "Kimbeaux",
        "email": "piller.bryan@gmail.com"
      },
      {
        "name": "Junior le Bandit",
        "email": "yangaman01@gmail.com"
      },
      {
        "name": "Aikensama",
        "email": "jojopmetness@gmail.com"
      }
    ]
  },
  {
    "name": "Whitecross Gaming",
    "lineup": [
      {
        "name": "ElStevyyy",
        "email": "stevenvaglio@hotmail.fr"
      },
      {
        "name": "Bambamx",
        "email": "whitecrossgaming@outlook.com"
      },
      {
        "name": "PXL Gilouuu",
        "email": "gil.perolini@hotmail.ch"
      },
      {
        "name": "PXL Ackyro",
        "email": "Florianstraccia@hotmail.ch"
      }
    ]
  }
]